LICENSE
web3_multi_provider/__init__.py
web3_multi_provider/async_http_provider_proxy.py
web3_multi_provider/async_multi_http_provider.py
web3_multi_provider/cl_client_proxy.py
web3_multi_provider/exceptions.py
web3_multi_provider/http_provider_proxy.py
web3_multi_provider/http_session_manager_proxy.py
web3_multi_provider/metrics.py
web3_multi_provider/metrics_decorator.py
web3_multi_provider/multi_http_provider.py
web3_multi_provider/py.typed
web3_multi_provider/util.py
web3_multi_provider-2.2.1.dist-info/LICENSE
web3_multi_provider-2.2.1.dist-info/METADATA
web3_multi_provider-2.2.1.dist-info/WHEEL
web3_multi_provider-2.2.1.dist-info/RECORD
