Metadata-Version: 2.1
Name: web3-multi-provider
Version: 2.2.1
Summary: Web3py provider that makes it easy to switch between different blockchain nodes to make sure application will be be online if main blockchain node will be unavailable.
License: MIT
Author: Raman
Author-email: raman.s@lido.fi
Requires-Python: >=3.12,<4
Classifier: License :: OSI Approved :: MIT License
Classifier: Programming Language :: Python :: 3
Classifier: Programming Language :: Python :: 3.12
Provides-Extra: metrics
Requires-Dist: prometheus-client (>=0.21.1,<0.22.0) ; extra == "metrics"
Requires-Dist: web3 (>=7,<8)
